invenio_theme/__init__.py
invenio_theme/config.py
invenio_theme/ext.py
invenio_theme/icons.py
invenio_theme/proxies.py
invenio_theme/shared.py
invenio_theme/views.py
invenio_theme/webpack.py
invenio_theme/assets/bootstrap3/js/invenio_theme/admin.js
invenio_theme/assets/bootstrap3/js/invenio_theme/base.js
invenio_theme/assets/bootstrap3/scss/invenio_theme/admin.scss
invenio_theme/assets/bootstrap3/scss/invenio_theme/angular.scss
invenio_theme/assets/bootstrap3/scss/invenio_theme/body.scss
invenio_theme/assets/bootstrap3/scss/invenio_theme/cover.scss
invenio_theme/assets/bootstrap3/scss/invenio_theme/footer.scss
invenio_theme/assets/bootstrap3/scss/invenio_theme/header.scss
invenio_theme/assets/bootstrap3/scss/invenio_theme/input-icon.scss
invenio_theme/assets/bootstrap3/scss/invenio_theme/navbar.scss
invenio_theme/assets/bootstrap3/scss/invenio_theme/styles.scss
invenio_theme/assets/bootstrap3/scss/invenio_theme/theme.scss
invenio_theme/assets/bootstrap3/scss/invenio_theme/type.scss
invenio_theme/assets/bootstrap3/scss/invenio_theme/variables.scss
invenio_theme/assets/semantic-ui/js/invenio_theme/Media.js
invenio_theme/assets/semantic-ui/js/invenio_theme/admin.js
invenio_theme/assets/semantic-ui/js/invenio_theme/base.js
invenio_theme/assets/semantic-ui/js/invenio_theme/templates.js
invenio_theme/assets/semantic-ui/js/invenio_theme/theme.js
invenio_theme/assets/semantic-ui/js/invenio_theme/truncate.js
invenio_theme/assets/semantic-ui/less/invenio_theme/theme.config.example
invenio_theme/assets/semantic-ui/less/invenio_theme/fonts/Lato-Bold.eot
invenio_theme/assets/semantic-ui/less/invenio_theme/fonts/Lato-Bold.ttf
invenio_theme/assets/semantic-ui/less/invenio_theme/fonts/Lato-Bold.woff
invenio_theme/assets/semantic-ui/less/invenio_theme/fonts/Lato-Bold.woff2
invenio_theme/assets/semantic-ui/less/invenio_theme/fonts/Lato-BoldItalic.eot
invenio_theme/assets/semantic-ui/less/invenio_theme/fonts/Lato-BoldItalic.ttf
invenio_theme-4.5.0.dist-info/licenses/AUTHORS.rst
invenio_theme-4.5.0.dist-info/licenses/LICENSE
invenio_theme-4.5.0.dist-info/METADATA
invenio_theme-4.5.0.dist-info/WHEEL
invenio_theme-4.5.0.dist-info/entry_points.txt
invenio_theme-4.5.0.dist-info/top_level.txt
invenio_theme-4.5.0.dist-info/RECORD
