Metadata-Version: 2.4
Name: invenio-theme
Version: 4.5.0
Summary: "Invenio standard theme."
Home-page: https://github.com/inveniosoftware/invenio-theme
Author: Invenio Collaboration
Author-email: info@inveniosoftware.org
License: MIT
Keywords: invenio
Platform: any
Classifier: Development Status :: 5 - Production/Stable
Requires-Python: >=3.7
License-File: LICENSE
License-File: AUTHORS.rst
Requires-Dist: Flask-Menu>=1.0.0
Requires-Dist: invenio-assets<5.0.0,>=4.0.0
Requires-Dist: invenio-base<3.0.0,>=2.0.0
Requires-Dist: invenio-i18n<4.0.0,>=3.0.0
Requires-Dist: jsmin>=3.0.0
Provides-Extra: tests
Requires-Dist: pytest-black-ng>=0.4.0; extra == "tests"
Requires-Dist: pytest-invenio<4.0.0,>=3.0.0; extra == "tests"
Requires-Dist: Sphinx>=5; extra == "tests"
Provides-Extra: docs
Dynamic: license-file
